{
  "aor": 0.002174505494505494,
  "aqi": 0.012420989120879121,
  "bids_meta": {
    "RepetitionTime": 2.0,
    "TaskName": "stop signal",
    "dataset": "ds000008",
    "modality": "bold",
    "run_id": 3,
    "subject_id": "13",
    "task_id": "stopsignal"
  },
  "dummy_trs": 0,
  "dvars_nstd": 31.74454067281769,
  "dvars_std": 1.2580212690607728,
  "dvars_vstd": 0.9946330312707191,
  "efc": 0.49617306685371304,
  "fber": 2980.259765625,
  "fd_mean": 0.09823425317869099,
  "fd_num": 6,
  "fd_perc": 3.2967032967032965,
  "fwhm_avg": 1.5803408,
  "fwhm_x": 1.6060576,
  "fwhm_y": 1.7817888,
  "fwhm_z": 1.353176,
  "gcor": 0.0109591,
  "gsr_x": -0.004704847000539303,
  "gsr_y": 0.0278184674680233,
  "provenance": {
    "md5sum": "daf9cf61d6f7ebdb8b203b4b4beed88f",
    "settings": {
      "fd_thres": 0.2,
      "testing": false
    },
    "software": "mriqc",
    "version": "21.0.0rc2",
    "webapi_port": null,
    "webapi_url": "https://mriqc.nimh.nih.gov/api/v1"
  },
  "size_t": 182,
  "size_x": 64,
  "size_y": 64,
  "size_z": 30,
  "snr": 6.487643499877725,
  "spacing_tr": 2.0,
  "spacing_x": 3.125,
  "spacing_y": 3.125,
  "spacing_z": 5.0,
  "summary_bg_k": 85.15187307446207,
  "summary_bg_mad": 4.700338361977734,
  "summary_bg_mean": 27.477638244628906,
  "summary_bg_median": 12.505495071411133,
  "summary_bg_n": 73045.0,
  "summary_bg_p05": 8.972527503967285,
  "summary_bg_p95": 80.32637634277349,
  "summary_bg_stdv": 54.87835693359375,
  "summary_fg_k": 3.0775030932419707,
  "summary_fg_mad": 92.36537618786288,
  "summary_fg_mean": 708.7803344726562,
  "summary_fg_median": 701.7939453125,
  "summary_fg_n": 20766.0,
  "summary_fg_p05": 554.1470031738281,
  "summary_fg_p95": 878.1662292480469,
  "summary_fg_stdv": 108.17133331298828,
  "tsnr": 58.82110271463171
}