{
  "aor": 0.0014286263736263734,
  "aqi": 0.015620831373626371,
  "bids_meta": {
    "RepetitionTime": 2.0,
    "TaskName": "stop signal",
    "dataset": "ds000008",
    "modality": "bold",
    "run_id": 1,
    "subject_id": "06",
    "task_id": "stopsignal"
  },
  "dummy_trs": 0,
  "dvars_nstd": 30.42678077453038,
  "dvars_std": 1.1907326158011042,
  "dvars_vstd": 0.978357119281768,
  "efc": 0.4822363788959561,
  "fber": 2602.395263671875,
  "fd_mean": 0.12857348525952686,
  "fd_num": 18,
  "fd_perc": 9.89010989010989,
  "fwhm_avg": 1.6180333333333332,
  "fwhm_x": 1.709456,
  "fwhm_y": 1.818096,
  "fwhm_z": 1.326548,
  "gcor": 0.0101992,
  "gsr_x": 0.002291344339028001,
  "gsr_y": 0.023618945851922035,
  "provenance": {
    "md5sum": "8a1559cb1c60f0460961df18b5273628",
    "settings": {
      "fd_thres": 0.2,
      "testing": false
    },
    "software": "mriqc",
    "version": "21.0.0rc2",
    "webapi_port": null,
    "webapi_url": "https://mriqc.nimh.nih.gov/api/v1"
  },
  "size_t": 182,
  "size_x": 64,
  "size_y": 64,
  "size_z": 30,
  "snr": 7.0465762930019045,
  "spacing_tr": 2.0,
  "spacing_x": 3.125,
  "spacing_y": 3.125,
  "spacing_z": 5.0,
  "summary_bg_k": 40.21194571889787,
  "summary_bg_mad": 5.95484706137807,
  "summary_bg_mean": 31.3897762298584,
  "summary_bg_median": 13.741758346557617,
  "summary_bg_n": 77281.0,
  "summary_bg_p05": 8.604395866394043,
  "summary_bg_p95": 111.63736724853516,
  "summary_bg_stdv": 53.98720169067383,
  "summary_fg_k": 3.0251553218414458,
  "summary_fg_mad": 91.56290325855943,
  "summary_fg_mean": 716.5888061523438,
  "summary_fg_median": 711.2527465820312,
  "summary_fg_n": 17711.0,
  "summary_fg_p05": 575.0796813964844,
  "summary_fg_p95": 877.3846435546875,
  "summary_fg_stdv": 100.9330825805664,
  "tsnr": 49.529439305188134
}